boring/__init__.py
boring/__main__.py
boring/cli.py
boring/config.py
boring/dir.py
boring/exception.py
boring/http.py
boring/reloader.py
boring/server.py
boring/utils.py
boring/wsgi.py
boring/middleware/__init__.py
boring/middleware/statics.py
boring-1.0.2.dist-info/LICENSE
boring-1.0.2.dist-info/METADATA
boring-1.0.2.dist-info/WHEEL
boring-1.0.2.dist-info/entry_points.txt
boring-1.0.2.dist-info/top_level.txt
boring-1.0.2.dist-info/RECORD
