Metadata-Version: 2.1
Name: boring
Version: 1.0.2
Summary: A small HTTP web server for wsgi compatible apps
Home-page: https://github.com/horlarwumhe/boring
Author: Horlarwumhe
Author-email: amachiever4real@gmail.com
License: UNKNOWN
Platform: UNKNOWN
Classifier: Programming Language :: Python :: 3
Classifier: License :: OSI Approved :: MIT License
Classifier: Operating System :: OS Independent
Requires-Python: >=3.7
